winrt/_winrt_microsoft_graphics_directx.cp313-win_amd64.pyd
winrt/_winrt_microsoft_graphics_directx.pyi
winrt/microsoft/graphics/directx/__init__.py
winrt/microsoft/graphics/directx/py.typed
winrt_Microsoft.Graphics.DirectX-2.3.0.dist-info/METADATA
winrt_Microsoft.Graphics.DirectX-2.3.0.dist-info/WHEEL
winrt_Microsoft.Graphics.DirectX-2.3.0.dist-info/top_level.txt
winrt_Microsoft.Graphics.DirectX-2.3.0.dist-info/RECORD
